# 付録B.17: JVMアーキテクチャとバイトコード

## 概要

本付録では、Java Virtual Machine（JVM）の内部アーキテクチャとバイトコード命令について詳細に解説します。Javaプログラムがどのようにコンパイルされ、実行されるのか、JVMがどのようにメモリを管理し、最適化を行うのかを理解することで、より効率的なJavaプログラムを書けるようになります。

**対象読者**: Javaの基礎を理解し、JVMの内部動作に興味がある開発者  
**前提知識**: 第1章「Javaプログラミング入門」の内容、基本的なコンピュータアーキテクチャ  
**関連章**: 第1章、第2章（メモリ管理）、付録B.02（ガベージコレクション）

## なぜJVMアーキテクチャの理解が重要なのか

### 実際のパフォーマンス問題と解決

**問題1: 予期しないOutOfMemoryError**
```java
// ヒープ不足の典型例
public class MemoryLeak {
    private static final List<Object> cache = new ArrayList<>();
    
    public void processData() {
        for (int i = 0; i < 1000000; i++) {
            cache.add(new BigObject()); // ヒープ圧迫
        }
    }
}
```
**問題**: ヒープ領域の理解不足によりメモリリークが発生
**実際の影響**: 本番環境でサービス停止、緊急対応が必要

**問題2: JITコンパイラの最適化阻害**
```java
// 最適化されにくいコード
public class OptimizationBarrier {
    public int calculate(int n) {
        if (Math.random() > 0.5) { // 予測不可能な分岐
            return complexCalculation(n);
        } else {
            return simpleCalculation(n);
        }
    }
}
```
**問題**: ホットスポット検出の阻害により性能が向上しない
**影響**: CPU集約処理で期待する性能の50%以下に

**問題3: クラスローディングボトルネック**
```java
// 動的クラスローディングによる遅延
public class DynamicLoading {
    public void processRequest(String className) {
        try {
            Class<?> clazz = Class.forName(className); // 毎回ロード
            Object instance = clazz.getDeclaredConstructor().newInstance();
            processObject(instance);
        } catch (Exception e) {
            // エラーハンドリング
        }
    }
}
```
**問題**: 不適切なクラスローディングによりレスポンス遅延
**実際の事例**: Webアプリケーションで初回リクエストが数秒かかる

### ビジネスへの実際の影響

**実際のシステム障害事例**

JVMの理解不足により、多くの組織で深刻なシステム障害が発生しています。某ECサイトでは、GC停止時間の長期化によりタイムアウトが多発し、売上機会の大きな損失を被りました。金融システムでは、メタスペース不足によりシステムの再起動が必要となり、重要な取引処理が停止しました。ゲームサーバーでは、JIT最適化不足によりレスポンス遅延が発生し、最終的にユーザーの離脱を招きました。

**チューニングによる改善効果**

適切なJVMチューニングにより、これらの問題は劇的に改善されます。ヒープサイズの最適化により、GC時間を90%削減し、レスポンスの安定化を実現しました。JITコンパイラの設定最適化では、CPU集約処理において3倍の高速化を達成しました。クラスローディングの最適化では、アプリケーションの起動時間を80%短縮することができました。

**開発・運用への影響**

JVMアーキテクチャの理解は、開発と運用の両面で大きな影響をもたらします。デバッグ効率については、JVMツールを活用することで問題解決時間を大幅に短縮できます。監視・アラートでは、適切なメトリクスを設定することでプロアクティブな対応が可能になります。容量計画では、メモリ使用パターンを理解することで適切なサイジングを行うことができます。

---

## JVMアーキテクチャの全体像

### JVMの主要コンポーネント

```
┌─────────────────────────────────────────────────────────────┐
│                         JVM                                   │
├─────────────────────────────────────────────────────────────┤
│  Class Loader Subsystem                                      │
│  ├─ Bootstrap Class Loader                                   │
│  ├─ Extension Class Loader                                   │
│  └─ Application Class Loader                                 │
├─────────────────────────────────────────────────────────────┤
│  Runtime Data Areas                                          │
│  ├─ Method Area (Metaspace)                                  │
│  ├─ Heap                                                     │
│  ├─ Java Stacks                                             │
│  ├─ PC Registers                                            │
│  └─ Native Method Stacks                                    │
├─────────────────────────────────────────────────────────────┤
│  Execution Engine                                            │
│  ├─ Interpreter                                             │
│  ├─ JIT Compiler                                            │
│  │  ├─ C1 Compiler (Client)                                 │
│  │  └─ C2 Compiler (Server)                                 │
│  └─ Garbage Collector                                       │
├─────────────────────────────────────────────────────────────┤
│  Native Interface                                            │
│  └─ JNI (Java Native Interface)                             │
└─────────────────────────────────────────────────────────────┘
```

### クラスローディングのプロセス

```java
// クラスローダーの階層構造を確認
public class ClassLoaderHierarchy {
    public static void main(String[] args) {
        // システムクラスローダー
        ClassLoader systemLoader = ClassLoader.getSystemClassLoader();
        System.out.println("System ClassLoader: " + systemLoader);
        
        // 拡張クラスローダー
        ClassLoader extLoader = systemLoader.getParent();
        System.out.println("Extension ClassLoader: " + extLoader);
        
        // ブートストラップクラスローダー（nullで表される）
        ClassLoader bootstrapLoader = extLoader.getParent();
        System.out.println("Bootstrap ClassLoader: " + bootstrapLoader);
        
        // 各クラスのローダーを確認
        System.out.println("\nClass Loaders for different classes:");
        System.out.println("String: " + String.class.getClassLoader());
        System.out.println("HashMap: " + java.util.HashMap.class.getClassLoader());
        System.out.println("This class: " + ClassLoaderHierarchy.class.getClassLoader());
    }
}
```

### カスタムクラスローダー

```java
public class CustomClassLoader extends ClassLoader {
    private final String classPath;
    
    public CustomClassLoader(String classPath) {
        this.classPath = classPath;
    }
    
    @Override
    protected Class<?> findClass(String name) throws ClassNotFoundException {
        try {
            // クラスファイルのバイト配列を読み込む
            byte[] classData = loadClassData(name);
            
            // バイト配列からクラスを定義
            return defineClass(name, classData, 0, classData.length);
        } catch (IOException e) {
            throw new ClassNotFoundException("Failed to load class: " + name, e);
        }
    }
    
    private byte[] loadClassData(String className) throws IOException {
        String fileName = classPath + "/" + className.replace('.', '/') + ".class";
        try (InputStream is = new FileInputStream(fileName);
             ByteArrayOutputStream baos = new ByteArrayOutputStream()) {
            
            byte[] buffer = new byte[4096];
            int bytesRead;
            while ((bytesRead = is.read(buffer)) != -1) {
                baos.write(buffer, 0, bytesRead);
            }
            
            return baos.toByteArray();
        }
    }
}
```

---

## ランタイムデータエリア

### メソッドエリア（Metaspace）

```java
// メタスペースに格納される情報
public class MetaspaceContent {
    // クラスメタデータ
    private static final String CLASS_VERSION = "1.0";
    
    // 静的変数
    private static int instanceCount = 0;
    
    // メソッド情報
    public void demonstrateMetaspace() {
        // リフレクションでメタデータにアクセス
        Class<?> clazz = this.getClass();
        
        // フィールド情報
        Arrays.stream(clazz.getDeclaredFields())
            .forEach(field -> System.out.println("Field: " + field));
        
        // メソッド情報
        Arrays.stream(clazz.getDeclaredMethods())
            .forEach(method -> System.out.println("Method: " + method));
        
        // アノテーション情報
        Arrays.stream(clazz.getAnnotations())
            .forEach(annotation -> System.out.println("Annotation: " + annotation));
    }
}

// メタスペースのサイズ設定
// -XX:MetaspaceSize=128m -XX:MaxMetaspaceSize=256m
```

### ヒープメモリの構造

```java
// ヒープメモリの世代別構造
public class HeapStructure {
    public static void demonstrateGenerations() {
        // Young Generation (Eden + Survivor)
        for (int i = 0; i < 1000; i++) {
            // 短命なオブジェクト
            String temp = "Temporary " + i;
        }
        
        // Old Generation
        List<String> longLived = new ArrayList<>();
        for (int i = 0; i < 100; i++) {
            // 長寿命なオブジェクト
            longLived.add("Long-lived " + i);
        }
        
        // ヒープ情報の取得
        MemoryMXBean memoryBean = ManagementFactory.getMemoryMXBean();
        MemoryUsage heapUsage = memoryBean.getHeapMemoryUsage();
        
        System.out.println("Heap Memory Usage:");
        System.out.println("  Init: " + heapUsage.getInit() / 1024 / 1024 + " MB");
        System.out.println("  Used: " + heapUsage.getUsed() / 1024 / 1024 + " MB");
        System.out.println("  Committed: " + heapUsage.getCommitted() / 1024 / 1024 + " MB");
        System.out.println("  Max: " + heapUsage.getMax() / 1024 / 1024 + " MB");
    }
}
```

### スタックとフレーム

```java
public class StackFrameDemo {
    // 各メソッド呼び出しでスタックフレームが作成される
    public static void main(String[] args) {
        int result = method1(10);
        System.out.println("Result: " + result);
    }
    
    private static int method1(int x) {
        int local1 = x * 2;
        return method2(local1);
    }
    
    private static int method2(int y) {
        int local2 = y + 5;
        printStackTrace();  // スタックトレースを表示
        return local2;
    }
    
    private static void printStackTrace() {
        System.out.println("Stack Trace:");
        StackTraceElement[] stackTrace = Thread.currentThread().getStackTrace();
        for (StackTraceElement element : stackTrace) {
            System.out.println("  " + element);
        }
    }
}

// スタックフレームの内容
/*
Each Stack Frame contains:
- Local Variable Array
- Operand Stack
- Frame Data (constant pool reference, exception handling info)
*/
```

---

## バイトコード命令セット

### 基本的なバイトコード

```java
// Javaソースコード
public class BytecodeExample {
    public int add(int a, int b) {
        return a + b;
    }
    
    public int multiply(int x, int y) {
        int result = 0;
        for (int i = 0; i < y; i++) {
            result += x;
        }
        return result;
    }
}

// javap -c BytecodeExample でバイトコードを確認
/*
public int add(int, int);
  Code:
     0: iload_1        // 第1引数をスタックにロード
     1: iload_2        // 第2引数をスタックにロード
     2: iadd           // 加算
     3: ireturn        // 結果を返す

public int multiply(int, int);
  Code:
     0: iconst_0       // 定数0をスタックにプッシュ
     1: istore_3       // ローカル変数3（result）に格納
     2: iconst_0       // 定数0をスタックにプッシュ
     3: istore        4 // ローカル変数4（i）に格納
     5: iload         4 // iをロード
     7: iload_2        // yをロード
     8: if_icmpge     21 // i >= yなら21へジャンプ
    11: iload_3        // resultをロード
    12: iload_1        // xをロード
    13: iadd           // result + x
    14: istore_3       // resultに格納
    15: iinc          4, 1 // i++
    18: goto          5  // ループの開始へ
    21: iload_3        // resultをロード
    22: ireturn        // 返す
*/
```

### バイトコード命令のカテゴリ

```java
public class BytecodeInstructions {
    // 1. ロード/ストア命令
    public void loadStoreExample() {
        int a = 10;      // bipush 10, istore_1
        long b = 20L;    // ldc2_w 20, lstore_2
        float c = 3.14f; // ldc 3.14, fstore 4
        double d = 2.71; // ldc2_w 2.71, dstore 5
        Object o = null; // aconst_null, astore 7
    }
    
    // 2. 算術命令
    public void arithmeticExample() {
        int sum = 5 + 3;     // iadd
        int diff = 10 - 4;   // isub
        int prod = 6 * 7;    // imul
        int quot = 20 / 4;   // idiv
        int rem = 17 % 5;    // irem
        int neg = -sum;      // ineg
    }
    
    // 3. 型変換命令
    public void typeConversionExample() {
        int i = 100;
        long l = i;      // i2l
        float f = i;     // i2f
        double d = i;    // i2d
        byte b = (byte)i;// i2b
        short s = (short)i; // i2s
    }
    
    // 4. オブジェクト操作命令
    public void objectExample() {
        String s = new String();  // new, dup, invokespecial
        int length = s.length();  // invokevirtual
        Class<?> clazz = s.getClass(); // invokevirtual
        boolean b = s instanceof String; // instanceof
    }
    
    // 5. 制御フロー命令
    public void controlFlowExample(int x) {
        if (x > 0) {        // ifle
            // positive
        } else if (x < 0) { // ifge
            // negative
        } else {
            // zero
        }
        
        for (int i = 0; i < 10; i++) {  // goto, if_icmpge
            // loop body
        }
    }
}
```

### invokedynamic命令

```java
// ラムダ式とinvokedynamic
public class InvokeDynamicExample {
    public static void main(String[] args) {
        // ラムダ式はinvokedynamicを使用
        Runnable r = () -> System.out.println("Lambda");
        r.run();
        
        // メソッド参照もinvokedynamic
        Consumer<String> printer = System.out::println;
        printer.accept("Method Reference");
    }
}

// バイトコード（簡略版）
/*
invokedynamic #4,  0  // InvokeDynamic #0:run:()Ljava/lang/Runnable;
astore_1
aload_1
invokeinterface #5,  1  // InterfaceMethod java/lang/Runnable.run:()V
*/
```

---

## JITコンパイラ

### コンパイルレベルとティアリング

```java
// JITコンパイルの確認
// -XX:+PrintCompilation -XX:+UnlockDiagnosticVMOptions -XX:+PrintInlining
public class JITCompilationDemo {
    private static final int ITERATIONS = 100_000;
    
    public static void main(String[] args) {
        // ウォームアップ
        for (int i = 0; i < 10_000; i++) {
            compute(i);
        }
        
        // 測定
        long start = System.nanoTime();
        for (int i = 0; i < ITERATIONS; i++) {
            compute(i);
        }
        long end = System.nanoTime();
        
        System.out.println("Time: " + (end - start) / 1_000_000 + " ms");
    }
    
    // ホットメソッド（JITコンパイル対象）
    private static int compute(int n) {
        return n * n + n / 2;
    }
}

// コンパイルレベル
/*
Level 0: Interpreter
Level 1: C1 with full optimization (no profiling)
Level 2: C1 with invocation and backedge counters
Level 3: C1 with full profiling
Level 4: C2 (Server compiler)
*/
```

### JITコンパイラの最適化

```java
public class JITOptimizations {
    // 1. メソッドインライン化
    public int inlineExample(int x) {
        return square(x) + double(x);  // 両メソッドがインライン化される
    }
    
    private int square(int n) {
        return n * n;
    }
    
    private int double(int n) {
        return n * 2;
    }
    
    // 2. デッドコード除去
    public void deadCodeElimination() {
        int unused = 100 * 200;  // 除去される
        boolean flag = false;
        if (flag) {
            // このブロックは除去される
            System.out.println("Never executed");
        }
    }
    
    // 3. ループ最適化
    public int loopOptimization(int[] array) {
        int sum = 0;
        int length = array.length;  // ループ不変式の移動
        
        // ループアンローリング
        for (int i = 0; i < length - 3; i += 4) {
            sum += array[i];
            sum += array[i + 1];
            sum += array[i + 2];
            sum += array[i + 3];
        }
        
        // 残りの要素
        for (int i = length & ~3; i < length; i++) {
            sum += array[i];
        }
        
        return sum;
    }
    
    // 4. エスケープ解析
    public int escapeAnalysis() {
        Point p = new Point(10, 20);  // スタック割り当て可能
        return p.x + p.y;
    }
    
    static class Point {
        final int x, y;
        Point(int x, int y) {
            this.x = x;
            this.y = y;
        }
    }
}
```

### プロファイルガイド最適化

```java
// -XX:+UnlockDiagnosticVMOptions -XX:+LogCompilation
public class ProfileGuidedOptimization {
    private static final Random random = new Random();
    
    public static void main(String[] args) {
        for (int i = 0; i < 100_000; i++) {
            processValue(random.nextInt(100));
        }
    }
    
    // プロファイル情報に基づく最適化
    private static void processValue(int value) {
        // 90%の確率でこの分岐に入る場合
        if (value < 90) {
            // JITはこのパスを最適化
            commonPath(value);
        } else {
            // まれなパスは最適化されない
            rarePath(value);
        }
    }
    
    private static void commonPath(int value) {
        // 頻繁に実行されるコード
    }
    
    private static void rarePath(int value) {
        // まれに実行されるコード
    }
}
```

---

## メモリモデルとバリア

### メモリバリアの挿入

```java
public class MemoryBarriers {
    // volatileアクセスでのバリア
    private volatile int volatileField;
    private int normalField;
    
    public void demonstrateBarriers() {
        // Store-Store barrier
        normalField = 1;
        
        // Store-Load barrier (volatile write)
        volatileField = 2;
        
        // Load-Load barrier (volatile read)
        int v = volatileField;
        
        // Load-Store barrier
        normalField = v;
    }
}

// バイトコードレベルでのバリア
/*
volatileフィールドへの書き込み:
  putstatic/putfield
  // StoreStore barrier
  // StoreLoad barrier

volatileフィールドからの読み込み:
  getstatic/getfield
  // LoadLoad barrier
  // LoadStore barrier
*/
```

---

## 診断とモニタリング

### JVMフラグとツール

```java
public class JVMDiagnostics {
    public static void main(String[] args) {
        // JVM情報の取得
        RuntimeMXBean runtimeBean = ManagementFactory.getRuntimeMXBean();
        System.out.println("JVM Name: " + runtimeBean.getVmName());
        System.out.println("JVM Version: " + runtimeBean.getVmVersion());
        System.out.println("JVM Vendor: " + runtimeBean.getVmVendor());
        
        // JVMフラグの表示
        List<String> arguments = runtimeBean.getInputArguments();
        System.out.println("\nJVM Arguments:");
        arguments.forEach(arg -> System.out.println("  " + arg));
        
        // システムプロパティ
        System.out.println("\nSystem Properties:");
        System.getProperties().forEach((key, value) -> 
            System.out.println("  " + key + " = " + value));
    }
}

// 有用なJVMフラグ
/*
診断:
  -XX:+PrintGCDetails
  -XX:+PrintCompilation
  -XX:+TraceClassLoading
  -XX:+PrintAssembly (要hsdis)

パフォーマンス:
  -XX:+UseG1GC
  -XX:MaxGCPauseMillis=200
  -XX:+UseStringDeduplication
  -XX:+OptimizeStringConcat

デバッグ:
  -Xdebug
  -agentlib:jdwp=transport=dt_socket,server=y,suspend=n,address=5005
*/
```

---

## まとめ

JVMアーキテクチャとバイトコードの理解により：

1. **パフォーマンス最適化**: JITコンパイラの動作を意識したコード設計
2. **メモリ効率**: ヒープとスタックの使用パターンの最適化
3. **デバッグ能力**: バイトコードレベルでの問題解析
4. **チューニング**: 適切なJVMフラグの選択と設定
5. **深い理解**: Javaプログラムの実行メカニズムの完全な把握

これらの知識は、高性能なJavaアプリケーションの開発と、複雑な問題のトラブルシューティングにおいて非常に重要です。ただし、過度な最適化は避け、まずは正確で保守しやすいコードを書くことを優先すべきです。

## 実践的なサンプルコード

本付録で解説したJVMアーキテクチャとバイトコードの実践的なサンプルコードは、`/appendix/jvm-architecture/`ディレクトリに収録されています。クラスローダーの実装例、バイトコード解析ツール、JITコンパイラのベンチマークなど、JVMの内部動作を理解するための具体的なコード例を参照できます。